levox/__init__.py
levox/__main__.py
levox/cli.py
levox/main.py
levox/cli/__init__.py
levox/cli/commands.py
levox/cli/interactive.py
levox/cli/onboarding.py
levox/cli/output.py
levox/cli/reporting.py
levox/cli/services.py
levox/compliance/__init__.py
levox/compliance/advanced_trend_analyzer.py
levox/compliance/async_processor.py
levox/compliance/audit_logger.py
levox/compliance/cache_manager.py
levox/compliance/ccpa_analyzer.py
levox/compliance/company_manager.py
levox/compliance/compliance_alerter.py
levox/compliance/compliance_dashboard.py
levox/compliance/compliance_scoring.py
levox/compliance/data_compression.py
levox/compliance/evidence_generator.py
levox/compliance/evidence_store.py
levox/compliance/framework_engine.py
levox/compliance/framework_mapper.py
levox/compliance/gdpr_analyzer.py
levox/compliance/gdpr_mapper.py
levox/compliance/insights_engine.py
levox/compliance/models.py
levox/compliance/nl_insights.py
levox/compliance/optimized_store.py
levox/compliance/reporting.py
levox/compliance/storage_manager.py
levox/compliance/sync_service.py
levox/compliance/trend_analyzer.py
levox/core/__init__.py
levox/core/config.py
levox/core/engine.py
levox/core/exceptions.py
levox/core/feedback.py
levox/core/license_client.py
levox/core/rate_limiter.py
levox/core/scan_limiter.py
levox/core/security.py
levox/core/user_config.py
levox/detection/__init__.py
levox/detection/ast_analyzer.py
levox/detection/cfg_analyzer.py
levox/detection/context_analyzer.py
levox/detection/dataflow.py
levox/detection/ml_filter.py
levox/detection/regex_engine.py
levox/integrations/__init__.py
levox/integrations/ci_optimizer.py
levox/integrations/ci_tester.py
levox/integrations/config_manager.py
levox/integrations/git_tracker.py
levox/integrations/precommit.py
levox/integrations/repo_scanner.py
levox/integrations/template_generator.py
levox/models/__init__.py
levox/models/confidence.py
levox/models/detection_result.py
levox/models/repo_info.py
levox/parsers/__init__.py
levox/parsers/base.py
levox_cli-1.0.14.dist-info/licenses/LICENSE
levox_cli-1.0.14.dist-info/METADATA
levox_cli-1.0.14.dist-info/WHEEL
levox_cli-1.0.14.dist-info/entry_points.txt
levox_cli-1.0.14.dist-info/top_level.txt
levox_cli-1.0.14.dist-info/RECORD
